{"904728262877765632": ["DACA recipients are among Texas' selfless Hurricane Harvey heroes", "Some of the most selfless heroes in the aftermath of Harvey are DACA recipients"], "904728264614133761": ["Replica Nina ship sinks in Corpus Christi during Harvey's destruction", "Corpus Christi suffers another loss as the replica Nina ship sinks during Harvey"], "904728345006534656": ["Volunteers help evacuees during busy weekend after Harvey", "Volunteers were busy over the weekend helping evacuees of Harvey"], "904728823287205889": ["Specialty crops and vegetables damaged by Hurricane Harvey", "Harvey's impact on agriculture includes damage to specialty crops and vegetables"], "904732825449930752": ["Siri helps save girl stranded in Hurricane Harvey", "Technology plays a role in saving lives during Hurricane Harvey"], "904733179596165120": ["Donate and make breakfast for Harvey evacuees with this group", "Join this group in making breakfast for Harvey evacuees"], "904733259808071680": ["Harvey survivors fear what's next after narrow escapes", "Survivors of Harvey's destruction worry about what's to come"], "904733485138681856": ["Help Harvey survivors by spreading the word and donating", "Spread the word and donate to help the survivors of Harvey"], "904736854469169152": ["See what Hurricane Harvey left behind in this video", "Take a look at the aftermath of Harvey in this video"], "904736960060772352": ["Get a chicken wrap and drink for $4 with Harveys Canada coupons", "Save money on a chicken wrap and drink with these Harveys Canada coupons"]}