{"905692696953712641": ["Now hiring! Harvey restoration supervisors needed in Houston, TX. \ud83d\udea7", "Harvey restoration supervisors wanted in Houston, TX. Apply now! \ud83d\udea7"], "905693387092787200": ["Death toll from Harvey climbs as storm leaves Texas and inundates Louisiana. \ud83d\udc94", "As Harvey leaves Texas and inundates Louisiana, the death toll climbs. \ud83d\udc94"], "905697698484977664": ["Houston is open for business after Harvey, but other cities are still suffering. \ud83c\udf27\ufe0f", "While Houston bounces back after Harvey, other cities are still struggling. \ud83c\udf27\ufe0f"], "905702454465060865": ["Harvey likely to be first Texas hurricane landfall since Ike, nearly 9 years ago. \ud83c\udf00", "It's been nearly 9 years since Texas had a hurricane landfall, but Harvey is likely to break the streak. \ud83c\udf00"], "905706332468240384": ["Carolyn Nunn Harvey has jokes. \ud83d\ude02", "You have to hear Carolyn Nunn Harvey's jokes! \ud83d\ude02"], "905709457824518144": ["Check out the weekly summary for tornado activity. \ud83c\udf2a\ufe0f", "Stay up to date on tornado activity with this weekly summary. \ud83c\udf2a\ufe0f"], "905711016557682688": ["See the cost of Hurricane Harvey and its impact on the century. \ud83d\udcb0", "Data science, data viz, and big data show the cost of Hurricane Harvey and its impact on the century. \ud83d\udcb0"], "905714731385847808": ["Houston-area flood control chief saw no looming issues a year before Harvey. \ud83e\udd14", "A year before Harvey, the Houston-area flood control chief saw no issues on the horizon. \ud83e\udd14"], "905716323757547521": ["Gospel singer performs for Harvey evacuees in Conroe. \ud83c\udfa4", "Evacuees in Conroe get a special performance from a gospel singer in the wake of Harvey. \ud83c\udfa4"], "905717230373146624": ["Insurers and reinsurers struggle to assess the damage of Hurricane Harvey. \ud83c\udfed", "The damage of Hurricane Harvey is hard to assess for insurers and reinsurers. \ud83c\udfed"]}